Metadata-Version: 2.1
Name: django-oidc-sub
Version: 0.1
Summary: Django application for OIDC user authentication
Home-page: https://github.com/tpazderka/django-oidc-sub
Author: Tomas Pazderka
Author-email: tomas.pazderka@nic.cz
License: UNKNOWN
Platform: UNKNOWN
Provides-Extra: quality
